{
  "generator-jhipster": {
    "applicationType": "microservice",
    "baseName": "productorder",
    "jhipsterVersion": "7.4.1",
    "skipClient": true,
    "withAdminUi": false,
    "skipUserManagement": true,
    "skipCheckLengthOfIdentifier": false,
    "skipFakeData": false,
    "jhiPrefix": "jhi",
    "entitySuffix": "",
    "dtoSuffix": "DTO",
    "testFrameworks": ["cypress", "gatling", "cucumber"],
    "blueprints": [],
    "otherModules": [],
    "pages": [],
    "creationTimestamp": 1641309803470,
    "serviceDiscoveryType": "eureka",
    "reactive": false,
    "authenticationType": "jwt",
    "packageName": "com.bouziane_ilyas.store",
    "serverPort": "8081",
    "cacheProvider": "hazelcast",
    "enableHibernateCache": true,
    "databaseType": "sql",
    "devDatabaseType": "h2Disk",
    "prodDatabaseType": "mysql",
    "buildTool": "gradle",
    "serverSideOptions": [],
    "websocket": false,
    "searchEngine": false,
    "messageBroker": false,
    "enableSwaggerCodegen": false,
    "enableTranslation": true,
    "nativeLanguage": "en",
    "monorepository": true,
    "skipCommitHook": true,
    "jwtSecretKey": "YTI5YzFlZThmZDFkYmMyZDg4YmU3NTMwMjJjZDI2ZTQxNmIxOGY1MjVmMjM3MDBmN2VhN2NkMzAwYzlhY2UxNzU2ZDQxYzhmYmRiMmU4YmJhMGEyOTAzOTNjMTkyM2NjODNiOTJiOWJkNDA2ZWU0MTZiZWUzODNlMDQzM2Q4YjE=",
    "languages": ["en"],
    "enableGradleEnterprise": false,
    "entities": ["Product", "ProductCategory", "Customer", "ProductOrder", "OrderItem"],
    "lastLiquibaseTimestamp": 1641415325000
  }
}
